{
  "sequence": [
    {
      "unicode": "a∧(a∨b)",
      "scoreForHit": 0,
      "scoreForSkip": 0
    },
    {
      "unicode": "(a∧1)∧(a∨b)",
      "scoreForHit": -30,
      "scoreForSkip": 10,
      "substitution": { "left": "a", "right": "a∧1" }
    },
    {
      "unicode": "(a∧1)∧(¬a∨b)",
      "scoreForHit": 10,
      "scoreForSkip": -30
    },
    {
      "unicode": "a∧(1∧(¬a∨b))",
      "scoreForHit": -30,
      "scoreForSkip": 10,
      "substitution": { "left": "(a∧c)∧d", "right": "a∧(c∧d)" }
    },
    {
      "unicode": "a∧1",
      "scoreForHit": 10,
      "scoreForSkip": -30
    },
    {
      "unicode": "a∧(b∨¬b)",
      "scoreForHit": -30,
      "scoreForSkip": 10,
      "substitution": { "left": "1", "right": "b∨¬b" }
    }
  ]
}